find_git_repos.py
find_git_repos-1.1.0.dist-info/LICENSE
find_git_repos-1.1.0.dist-info/METADATA
find_git_repos-1.1.0.dist-info/WHEEL
find_git_repos-1.1.0.dist-info/entry_points.txt
find_git_repos-1.1.0.dist-info/top_level.txt
find_git_repos-1.1.0.dist-info/RECORD
