Metadata-Version: 2.1
Name: find-git-repos
Version: 1.1.0
Summary: CLI tool to find git repositories.
Home-page: https://github.com/acroz/find-git-repos
Author: Andrew Crozier
Author-email: wacrozier@gmail.com
License: MIT
Project-URL: GitHub, https://github.com/acroz/find-git-repos
Platform: UNKNOWN
Requires-Dist: termcolor
